tifffile.py
tiffile/__init__.py
tiffile/__main__.py
tiffile/lsm2bin.py
tiffile/tifffile.py
tiffile/tifffile_geodb.py
tiffile-2018.10.10.dist-info/LICENSE
tiffile-2018.10.10.dist-info/METADATA
tiffile-2018.10.10.dist-info/WHEEL
tiffile-2018.10.10.dist-info/entry_points.txt
tiffile-2018.10.10.dist-info/top_level.txt
tiffile-2018.10.10.dist-info/RECORD
