Metadata-Version: 2.1
Name: tiffile
Version: 2018.10.10
Summary: Read and write TIFF(r) files
Home-page: https://www.lfd.uci.edu/~gohlke/
Author: Christoph Gohlke
Author-email: cgohlke@uci.edu
License: BSD
Platform: any
Classifier: Development Status :: 4 - Beta
Classifier: License :: OSI Approved :: BSD License
Classifier: Intended Audience :: Science/Research
Classifier: Intended Audience :: Developers
Classifier: Operating System :: OS Independent
Classifier: Programming Language :: Python :: 2
Classifier: Programming Language :: Python :: 2.7
Classifier: Programming Language :: Python :: 3
Classifier: Programming Language :: Python :: 3.4
Classifier: Programming Language :: Python :: 3.5
Classifier: Programming Language :: Python :: 3.6
Classifier: Programming Language :: Python :: 3.7
Requires-Python: >=2.7
Requires-Dist: numpy (>=1.14)
Requires-Dist: imagecodecs (>=2018.9.22)
Requires-Dist: pathlib; python_version == "2.7"
Requires-Dist: enum34; python_version == "2.7"
Requires-Dist: futures; python_version == "2.7"
Provides-Extra: all
Requires-Dist: matplotlib (>=2.2); extra == 'all'
Provides-Extra: imshow
Requires-Dist: matplotlib (>=2.2); extra == 'imshow'
